TOMULATION/__init__.py
TOMULATION/leaf_dynamics.py
TOMULATION/main.py
TOMULATION/models.py
TOMULATION/partitioning.py
TOMULATION/phenology.py
TOMULATION/respiration.py
TOMULATION/root_dynamics.py
TOMULATION/stem_dynamics.py
TOMULATION/storage_organ_dynamics.py
TOMULATION/tomgrosim.py
TOMULATION-1.0.4.dist-info/LICENSE
TOMULATION-1.0.4.dist-info/METADATA
TOMULATION-1.0.4.dist-info/WHEEL
TOMULATION-1.0.4.dist-info/top_level.txt
TOMULATION-1.0.4.dist-info/RECORD
