Metadata-Version: 2.1
Name: TOMULATION
Version: 1.0.4
Summary: TOMULATION: Predicts tomato yield using actual measured photosynthesis or photosynthesis predicted from environmental information.
Home-page: https://github.com/marukory66/tomgrosim-on-pcse/tree/develop
Download-URL: https://github.com/marukory66/tomgrosim-on-pcse/tree/develop
Author: Naomichi Fujiuchi,Ryoga Maruko
Author-email: wlingwo@gmail.com
Maintainer: Naomichi Fujiuchi,Ryoga Maruko
Maintainer-email: wlingwo@gmail.com
License: GPL3
Classifier: Intended Audience :: Science/Research
Classifier: Programming Language :: Python :: 3
Classifier: Programming Language :: Python :: 3.8
Classifier: Programming Language :: Python :: 3 :: Only
License-File: LICENSE
Requires-Dist: pandas >=0.25
